pytorch_probgraph/__init__.py
pytorch_probgraph/dbm.py
pytorch_probgraph/dbn.py
pytorch_probgraph/hm.py
pytorch_probgraph/interaction.py
pytorch_probgraph/rbm.py
pytorch_probgraph/unitlayer.py
pytorch_probgraph/utils.py
PyTorch_ProbGraph-0.0.1.dist-info/LICENSE
PyTorch_ProbGraph-0.0.1.dist-info/METADATA
PyTorch_ProbGraph-0.0.1.dist-info/WHEEL
PyTorch_ProbGraph-0.0.1.dist-info/top_level.txt
PyTorch_ProbGraph-0.0.1.dist-info/RECORD
