Metadata-Version: 2.1
Name: PyTorch-ProbGraph
Version: 0.0.1
Summary: Hierarchical Probabilistic Graphical Models in PyTorch
Home-page: https://github.com/kpoeppel/pytorch_probgraph/
Author: Korbinian Poeppel, Hendrik Elvers
Author-email: korbinian.poeppel@tum.de, hendrik.elvers@tum.de
License: UNKNOWN
Platform: UNKNOWN
Classifier: Programming Language :: Python :: 3
Classifier: License :: OSI Approved :: MIT License
Classifier: Operating System :: OS Independent
Requires-Python: >=3.6
Requires-Dist: torch
Requires-Dist: numpy
Requires-Dist: matplotlib
Requires-Dist: tqdm
Requires-Dist: sphinx-rtd-theme
Requires-Dist: sphinx
Requires-Dist: setuptools
